sqlalchemy_ag_grid/__init__.py
sqlalchemy_ag_grid/const.py
sqlalchemy_ag_grid/query.py
sqlalchemy_ag_grid/util.py
sqlalchemy_ag_grid-0.0.2.dist-info/LICENSE
sqlalchemy_ag_grid-0.0.2.dist-info/METADATA
sqlalchemy_ag_grid-0.0.2.dist-info/WHEEL
sqlalchemy_ag_grid-0.0.2.dist-info/top_level.txt
sqlalchemy_ag_grid-0.0.2.dist-info/RECORD
